{
   "Description": {
      "Id": "Ammunition_LBX5_SABOT",
      "Name": "LB X-5 Ammo",
      "UIName": "APFSDS",
      "Details": "Small caliber ammunition designed for long range fire in an AC/2.",
      "Icon": null,
      "Cost": 0,
      "Rarity": 0,
      "Purchasable": false
   },
   "Type": "Normal",
   "Category": "LBX5",
	"DamagePerShot": -10,
   "HeatGenerated": 0,
   "AIBattleValue": 90,
   "HeatGeneratedModifier": 1,
   "ArmorDamageModifier": 1.0,
   "ISDamageModifier": 1.0,
   "CriticalDamageModifier": 1.25,
   	"MinRange": 0.0, 
	"MaxRange": 100.0, 
	"ShortRange": 25.0, 
	"MiddleRange": 50.0, 
	"LongRange": 75,
	"APDamage": 5,
	"APCriticalChanceMultiplier": 0.15
}